MANIFEST.in
setup.py
ansible_art.egg-info/PKG-INFO
ansible_art.egg-info/SOURCES.txt
ansible_art.egg-info/dependency_links.txt
ansible_art.egg-info/not-zip-safe
ansible_art.egg-info/top_level.txt
ansibleart/__init__.py
ansibleart/bin/ansible-art
ansibleart/data/ansible-art_playbook.yml.j2
ansibleart/data/ansible.cfg