Metadata-Version: 1.0
Name: ansible-art
Version: 0.3
Summary: A simple tool to apply role of ansible
Home-page: https://github.com/bbrfkr/ansible-art
Author: Tatsunori Saito
Author-email: bbrfkr@gmail.com
License: UNKNOWN
Platform: UNKNOWN
